pvs800_ardexa.py
pvs800_ardexa-1.1.7.dist-info/DESCRIPTION.rst
pvs800_ardexa-1.1.7.dist-info/METADATA
pvs800_ardexa-1.1.7.dist-info/RECORD
pvs800_ardexa-1.1.7.dist-info/WHEEL
pvs800_ardexa-1.1.7.dist-info/entry_points.txt
pvs800_ardexa-1.1.7.dist-info/metadata.json
pvs800_ardexa-1.1.7.dist-info/top_level.txt
