Metadata-Version: 2.0
Name: pvs800-ardexa
Version: 1.1.7
Summary: Collect from ABB PVS 800 Inverters and send the data to your cloud using Ardexa
Home-page: https://github.com/ardexa/pvs800-inverters
Author: Ardexa Pty Limited
Author-email: support@ardexa.com
License: UNKNOWN
Project-URL: Source, https://github.com/ardexa/pvs800-inverters/
Project-URL: Bug Reports, https://github.com/ardexa/pvs800-inverters/issues
Keywords: ABB solar inverter PVS800 ardexa
Platform: UNKNOWN
Classifier: License :: OSI Approved :: MIT License
Classifier: Programming Language :: Python :: 2
Classifier: Programming Language :: Python :: 2.7
Classifier: Programming Language :: Python :: 3
Classifier: Programming Language :: Python :: 3.4
Classifier: Programming Language :: Python :: 3.5
Classifier: Programming Language :: Python :: 3.6
Requires-Python: >=2.7
Requires-Dist: future
Requires-Dist: ardexaplugin
Requires-Dist: Click
